algoapi/__init__.py
algoapi/read_config.py
algoapi/fxconnect/__init__.py
algoapi/fxconnect/client/__init__.py
algoapi/fxconnect/client/fxcmconfig.py
algoapi/fxconnect/trade/__init__.py
algoapi/fxconnect/trade/delete_order.py
algoapi/fxconnect/trade/position.py
algoapi/fxconnect/trade/position_utils.py
algoapi/fxconnect/utils/__init__.py
algoapi/fxconnect/utils/custom_exception.py
algoapi/fxconnect/utils/utils.py
algoapi-0.0.4.dist-info/LICENSE
algoapi-0.0.4.dist-info/METADATA
algoapi-0.0.4.dist-info/WHEEL
algoapi-0.0.4.dist-info/top_level.txt
algoapi-0.0.4.dist-info/RECORD
