Metadata-Version: 2.1
Name: algoapi
Version: 0.0.4
Summary: Python project for Forexconnect API from FXCM
Author: Krishna Khatiwada
Author-email: krishna.khatiwada187@gmail.com
Project-URL: repository, https://github.com/KrishnaInvestment/algoapi
Classifier: Programming Language :: Python :: 3
Classifier: License :: OSI Approved :: MIT License
Classifier: Operating System :: OS Independent
Requires-Python: <=3.8
License-File: LICENSE
Requires-Dist: forexconnect
Requires-Dist: python-dotenv
Requires-Dist: pandas (==1.3.4)
